{
  "session_info": {
    "id": "THXB1",
    "name": "THXB1 - Invited Oral Presentation (Beam Instrumentation and Feedback)",
    "url": "https://proceedings.jacow.org/IPAC2013/html/thxb1.htm"
  },
  "papers": [
    {
      "paper_id": "THXB101",
      "title": "High Power Operation and Beam Instrumentations in J-PARC Synchrotrons",
      "authors": [
        "J-PARC",
        "KEK & JAEA",
        "Ibaraki-ken",
        "Japan"
      ],
      "institutions": [],
      "abstract": "Beam monitors developed and utilized at MR and RCS of J-PARC will be presented with emphasis on special characteristics for high intensity proton accelerator. Achieved beam characteristics and approach to improve beam intensity will be described in connection with the beam monitors. Usage of a transverse RF field to improve a duty factor of the slow extracted beam will be presented.",
      "presentation_url": "https://proceedings.jacow.org/IPAC2013/talks/thxb101_talk.pdf",
      "paper_url": "https://proceedings.jacow.org/IPAC2013/papers/thxb101.pdf",
      "poster_url": "https://proceedings.jacow.org/IPAC2013/posters/thxb101_poster.pdf",
      "doi": "https://doi.org/10.18429/JACoW-IPAC2013-THXB101",
      "page_number": "",
      "presentation_available": true,
      "paper_available": true,
      "poster_available": false
    }
  ],
  "paper_count": 1,
  "scrape_time": "2025-10-10 21:37:15"
}