{
  "session_info": {
    "id": "THYAB",
    "name": "THYAB - Invited Oral Presentations, Medical Accelerators and Applications",
    "url": "https://proceedings.jacow.org/PAC2013/html/thyab.htm"
  },
  "papers": [
    {
      "paper_id": "THYAB2",
      "title": "The US Carbon Therapy Initiative",
      "authors": [
        "LBNL",
        "Berkeley",
        "California",
        "USA",
        "This presentation will summarize the findings of a joint DOE-NIH workshop to be held in early January 2013",
        "outlining technical",
        "clinical",
        "and radiobiological issues key to establishing carbon therapy. This workshop is being commissioned as part of an initiative to restart the US hadron therapy program after many years' hiatus."
      ],
      "institutions": [],
      "abstract": "",
      "presentation_url": "https://proceedings.jacow.org/PAC2013/talks/thyab2_talk.pdf",
      "paper_url": "https://proceedings.jacow.org/PAC2013/papers/thyab2.pdf",
      "poster_url": "https://proceedings.jacow.org/PAC2013/posters/thyab2_poster.pdf",
      "doi": "https://doi.org/10.18429/JACoW-PAC2013-THYAB2",
      "page_number": "",
      "presentation_available": true,
      "paper_available": false,
      "poster_available": false
    }
  ],
  "paper_count": 1,
  "scrape_time": "2025-10-11 01:51:48"
}